README.rst
setup.py
src/AnthraxImage.egg-info/PKG-INFO
src/AnthraxImage.egg-info/SOURCES.txt
src/AnthraxImage.egg-info/dependency_links.txt
src/AnthraxImage.egg-info/entry_points.txt
src/AnthraxImage.egg-info/namespace_packages.txt
src/AnthraxImage.egg-info/requires.txt
src/AnthraxImage.egg-info/top_level.txt
src/anthrax/__init__.py
src/anthrax/image/__init__.py
src/anthrax/image/field.py